open_file_mock/__init__.py
open_file_mock/mock_open.py
open_file_mock/tests/__init__.py
open_file_mock/tests/test_open_file_mock.py
open_mock_file-1.0.2.dist-info/DESCRIPTION.rst
open_mock_file-1.0.2.dist-info/METADATA
open_mock_file-1.0.2.dist-info/RECORD
open_mock_file-1.0.2.dist-info/WHEEL
open_mock_file-1.0.2.dist-info/metadata.json
open_mock_file-1.0.2.dist-info/top_level.txt
