Metadata-Version: 2.0
Name: open-mock-file
Version: 1.0.2
Summary: Smart object for mocking open file calls, depends on file path
Home-page: https://github.com/PawelJ-PL/open-file-mock
Author: Pawel
Author-email: inne.poczta@gmail.com
License: MIT
Keywords: Python mock open file
Platform: UNKNOWN
Classifier: Development Status :: 5 - Production/Stable
Classifier: Intended Audience :: Developers
Classifier: License :: OSI Approved :: MIT License
Classifier: Programming Language :: Python :: 3 :: Only
Classifier: Topic :: Software Development :: Libraries
Requires-Python: >=3
Provides-Extra: test
Requires-Dist: coverage; extra == 'test'
Requires-Dist: nose; extra == 'test'
Requires-Dist: flake8; extra == 'test'
